dogui/__init__.py
dogui/dogui_core.py
dogui/dogui_kivy.py
dogui-0.1.3.dist-info/LICENSE
dogui-0.1.3.dist-info/METADATA
dogui-0.1.3.dist-info/WHEEL
dogui-0.1.3.dist-info/top_level.txt
dogui-0.1.3.dist-info/RECORD
