Metadata-Version: 2.1
Name: dogui
Version: 0.1.3
Summary: Code enabling easy gui creation for general applications 
Home-page: https://github.com/DovaX/dogui
Author: DovaX
Author-email: dovax.ai@gmail.com
License: UNKNOWN
Platform: UNKNOWN
Classifier: Programming Language :: Python :: 3
Classifier: License :: OSI Approved :: MIT License
Classifier: Operating System :: OS Independent
Requires-Python: >=3.6
Requires-Dist: Pillow
